optifik/__init__.py
optifik/analysis.py
optifik/fft.py
optifik/io.py
optifik/minmax.py
optifik/scheludko.py
optifik/utils.py
optifik-0.4.4.dist-info/licenses/LICENSE
optifik-0.4.4.dist-info/METADATA
optifik-0.4.4.dist-info/WHEEL
optifik-0.4.4.dist-info/top_level.txt
optifik-0.4.4.dist-info/RECORD
