Metadata-Version: 2.4
Name: optifik
Version: 0.4.4
Summary: Compute film thickness from interferometry
Author-email: François Boulogne <francois.boulogne@cnrs.fr>, Victor Ziapkoff <victor.ziapkoff@universite-paris-saclay.fr>
License-Expression: GPL-3.0
Project-URL: Documentation, https://sciunto.github.io/optifik/
Project-URL: Repository, https://github.com/sciunto-org/optifik
Project-URL: Issues, https://github.com/sciunto-org/optifik/issues
Requires-Python: >=3.10
License-File: LICENSE
Requires-Dist: numpy>=1.10.0
Requires-Dist: scipy>=1.1.0
Requires-Dist: matplotlib>=1.3.1
Requires-Dist: scikit-learn>=1.5
Provides-Extra: dev
Requires-Dist: pytest; extra == "dev"
Requires-Dist: pytest-cov; extra == "dev"
Requires-Dist: pyyaml; extra == "dev"
Requires-Dist: bumpver; extra == "dev"
Provides-Extra: docs
Requires-Dist: sphinx>=7.0; extra == "docs"
Requires-Dist: sphinx-rtd-theme>=2.0; extra == "docs"
Requires-Dist: numpydoc>=1.6; extra == "docs"
Requires-Dist: myst-parser>=2.0; extra == "docs"
Requires-Dist: sphinx-autodoc-typehints>=2.0; extra == "docs"
Requires-Dist: sphinx-copybutton>=0.5; extra == "docs"
Requires-Dist: sphinx-design>=0.5; extra == "docs"
Requires-Dist: nbsphinx; extra == "docs"
Requires-Dist: jupyter; extra == "docs"
Requires-Dist: ipykernel; extra == "docs"
Requires-Dist: sphinx-book-theme; extra == "docs"
Dynamic: license-file
